Metadata-Version: 2.1
Name: check-pdb-hook
Version: 0.0.9
Summary: Pre-commit hook to check exposed PDB statements in Python files.
Home-page: https://github.com/conorfalvey/check_pdb_hook
Author: Conor Falvey
Author-email: conor@carta.healthcare
License: MIT
Download-URL: https://github.com/conorfalvey/check_pdb_hook/archive/refs/tags/0.0.9.tar.gz
Platform: UNKNOWN
Classifier: License :: OSI Approved :: MIT License
Requires-Python: >=3.6.1
